{
  "brand": {
    "name": "Tax Star",
    "tones": [
      "Professional",
      "Supportive"
    ],
    "primaryCTA": "Book a Demo"
  },
  "structure": {
    "nav": [
      "By Role",
      "By Use Case",
      "About",
      "Resources",
      "Pricing"
    ],
    "keyPages": [
      {
        "path": "/accounting-practice-owners",
        "title": "Accounting Practice Owners"
      },
      {
        "path": "/tax-advisors",
        "title": "Tax Advisors"
      },
      {
        "path": "/by-role-erp-resellers",
        "title": "ERP Resellers"
      },
      {
        "path": "/corporate-tax-calculations",
        "title": "Corporate Tax Calculations"
      },
      {
        "path": "/internal-and-client-approvals",
        "title": "Internal and Client Approvals"
      },
      {
        "path": "/financial-statement-production",
        "title": "Financial Statements"
      },
      {
        "path": "/practice-and-deadline-management",
        "title": "Practice Management & Deadline"
      },
      {
        "path": "/about",
        "title": "About us"
      },
      {
        "path": "/faq",
        "title": "FAQ"
      },
      {
        "path": "/contact",
        "title": "Contact Us"
      },
      {
        "path": "/partners",
        "title": "Our Partners"
      },
      {
        "path": "/security-and-certifications",
        "title": "Security & Certifications"
      },
      {
        "path": "/tutorials",
        "title": "Video Tutorials"
      },
      {
        "path": "/podcast",
        "title": "Podcast"
      },
      {
        "path": "/webinar",
        "title": "Webinar"
      },
      {
        "path": "/blog",
        "title": "Blogs"
      },
      {
        "path": "/press",
        "title": "Press"
      },
      {
        "path": "/corporatetaxpenalties",
        "title": "Tax Penalties"
      },
      {
        "path": "/corporate-tax-guide",
        "title": "Corporate Tax Guide"
      },
      {
        "path": "/pricing",
        "title": "Pricing"
      }
    ],
    "footer": [
      "Book a Demo",
      "Log In",
      "Sign Up"
    ]
  },
  "audienceSignals": [
    "Accounting Practice Owners",
    "Tax Advisors",
    "ERP Resellers",
    "UAE businesses"
  ],
  "valueProps": [
    {
      "id": "v1",
      "text": "AI-powered Corporate Tax software for UAE businesses",
      "evidence": [
        "fact-3",
        "fact-7"
      ]
    },
    {
      "id": "v2",
      "text": "Automated returns, IFRS financial statement, and smart reminders",
      "evidence": [
        "fact-8",
        "fact-9"
      ]
    },
    {
      "id": "v3",
      "text": "E-Invoicing ensures seamless integration with corporate tax filing",
      "evidence": [
        "fact-10"
      ]
    },
    {
      "id": "v4",
      "text": "Zakat calculations built for KSA",
      "evidence": [
        "fact-11"
      ]
    },
    {
      "id": "v5",
      "text": "Automate Corporate Tax Calculations to save 40% of time",
      "evidence": [
        "fact-12"
      ]
    },
    {
      "id": "v6",
      "text": "Handle 30-40% more clients without hiring additional staff",
      "evidence": [
        "fact-13"
      ]
    }
  ],
  "pains": [
    "Compliance can feel stressful",
    "Failure to update registration documents results in penalties",
    "Manual tax calculations are time-consuming"
  ],
  "proof": [
    "Alpha Pro Partners logo",
    "JRBCA logo",
    "Legends Accounting logo",
    "Gulf School Finance logo",
    "Digital Tree logo",
    "Finsbury Accounting logo"
  ],
  "facts": [
    {
      "id": "fact-1",
      "text": "Tax Star provides an AI-powered compliance ecosystem.",
      "page": "Home",
      "evidence": "Your AI-Powered Compliance Ecosystem"
    },
    {
      "id": "fact-2",
      "text": "Tax Star offers a Corporate Tax Calculator.",
      "page": "Home",
      "evidence": "AI Powered Corporate Tax Calculator"
    },
    {
      "id": "fact-3",
      "text": "Tax Star's software is designed for UAE businesses.",
      "page": "Home",
      "evidence": "AI-powered Corporate Tax software for UAE businesses"
    },
    {
      "id": "fact-4",
      "text": "Tax Star includes E-Invoicing for UAE compliance.",
      "page": "Home",
      "evidence": "E-Invoicing in the UAE"
    },
    {
      "id": "fact-5",
      "text": "Tax Star includes Zakat calculations for KSA.",
      "page": "Home",
      "evidence": "Zakat in KSA"
    },
    {
      "id": "fact-6",
      "text": "Tax Star's toolkit helps stay compliant with ease.",
      "page": "Home",
      "evidence": "giving you everything you need to stay compliant with ease"
    },
    {
      "id": "fact-7",
      "text": "Tax Star offers a demo booking option.",
      "page": "Home",
      "evidence": "Book a Corporate Tax Demo"
    },
    {
      "id": "fact-8",
      "text": "Tax Star automates returns and IFRS financial statements.",
      "page": "Home",
      "evidence": "Automated returns, IFRS financial statement"
    },
    {
      "id": "fact-9",
      "text": "Tax Star provides smart reminders.",
      "page": "Home",
      "evidence": "smart reminders with Tax Star"
    },
    {
      "id": "fact-10",
      "text": "E-Invoicing ensures seamless integration with corporate tax filing.",
      "page": "Home",
      "evidence": "E-Invoicing that keeps your invoices FTA-compliant and ensures seamless integration with corporate tax filing"
    },
    {
      "id": "fact-11",
      "text": "Zakat calculations are designed to align with compliance reporting.",
      "page": "Home",
      "evidence": "Zakat calculations built for KSA, designed to align smoothly with your overall compliance reporting"
    },
    {
      "id": "fact-12",
      "text": "Automate Corporate Tax Calculations to save 40% of time.",
      "page": "Home",
      "evidence": "Save 40% of your time by automating corporate tax workflows"
    },
    {
      "id": "fact-13",
      "text": "Handle 30-40% more clients without hiring additional staff.",
      "page": "Home",
      "evidence": "Handle 30-40% more clients with automated workflows, all without hiring additional team members"
    },
    {
      "id": "fact-14",
      "text": "Failure to update registration documents results in AED 5,000 penalty.",
      "page": "Home",
      "evidence": "Failure to update your registration documents within 20 days of expiry will result in hefty penalties"
    },
    {
      "id": "fact-15",
      "text": "Tax Star notifies users of document expiry.",
      "page": "Home",
      "evidence": "Tax Star notifies you when they are due on a timely basis"
    },
    {
      "id": "fact-16",
      "text": "Tax Star eliminates the need for spreadsheets.",
      "page": "Home",
      "evidence": "Eliminate Spreadsheets"
    },
    {
      "id": "fact-17",
      "text": "Tax Star integrates with ERP systems.",
      "page": "Home",
      "evidence": "ERP Integrations"
    },
    {
      "id": "fact-18",
      "text": "Tax Star provides audit trails.",
      "page": "Home",
      "evidence": "Audit Trails"
    },
    {
      "id": "fact-19",
      "text": "Tax Star offers client and manager approval flows.",
      "page": "Home",
      "evidence": "Client & Manager Approval Flows"
    },
    {
      "id": "fact-20",
      "text": "Tax Star helps avoid penalties by ensuring compliance.",
      "page": "Home",
      "evidence": "Avoid penalties by staying compliant"
    }
  ]
}